datahandler_bhanu
