Metadata-Version: 2.1
Name: datahandler-bhanu
Version: 0.2
Summary: Handling Missing values in a given data set and imputing them.
Home-page: https://github.com/eternaldemon/datahandler
Author: Bhanu/eternal_demon
Author-email: aggarwal.bhanu02@gmail.com
License: UNKNOWN
Download-URL: https://github.com/eternaldemon/datahandler/archive/0.2.tar.gz
Platform: UNKNOWN
Classifier: Programming Language :: Python :: 3
Classifier: License :: OSI Approved :: MIT License
Classifier: Operating System :: OS Independent
Requires-Python: >=3.6
